{
 "resolved": {
  "006P700000Q15OU": "GAMUDA BERHAD",
  "0066700000yP7lZ": "FGV Holdings Berhad",
  "006P700000Zc18e": "Piraeus Port Authority",
  "006P700000FEVJR": "Changi Airport Group (Singapore) Pte. Ltd",
  "006P700000QFJwD": "NORTHPORT (MALAYSIA) BHD",
  "006P700000YlMxa": "Port Authority of NSW",
  "006P700000VLl6w": "Los Angeles County Metropolitan Transportation Authority",
  "006P700000YK67N": "Bank Rakyat",
  "006P700000Wkphs": "KWSP, EPF",
  "0066700000wdNe1": "Cebu Pacific Air",
  "006P700000YJlu7": "International SOS",
  "006P700000VnWhf": "Nidec Corporation",
  "006P700000YN6Nh": "The Hong Kong Jockey Club",
  "006P700000BV2eA": "Temasek",
  "006P700000Uxmk7": "Shenzhen WIK Domestic Appliances CO Ltd.",
  "006P700000NwbBd": "Hong Kong Aircraft Engineering Company Limited",
  "006P700000KTTO5": "MTR Corporation Limited",
  "006P700000Ltf02": "SATS Ltd",
  "006P700000H55TV": "Bandhan Bank",
  "006P700000aED8o": "Angel One Ltd",
  "006P700000ZxAjy": "VODAFONE IDEA LIMITED",
  "006P700000WXMP7": "Thiess",
  "006P700000YC92N": "Civeo Corporation",
  "006P700000YO8aM": "CIVEO PTY LTD",
  "006P700000Eo6QN": "National Procurement Commission of Papua New Guinea (PNG)",
  "006P700000GWfrf": "Techtronic Industries Company Limited",
  "006P700000QKfzN": "Scheme Financial Vehicle",
  "006P700000Ly6Mb": "Department of Justice",
  "006P700000Nh2xS": "AusNet",
  "006P700000X6hvK": "DOMINO'S PIZZA ENTERPRISES LIMITED",
  "006P700000Y1Ont": "ORASCOM CONSTRUCTION CO",
  "006P700000PIlWk": "Flydubai",
  "006P700000Z98IL": "ASYAD",
  "006P700000QvP7Z": "Arabian Industries LLC",
  "006P700000LtIUv": "Khansaheb",
  "006P700000VlPdp": "Wheelson Technologies",
  "006P700000RD9Ir": "SAMI",
  "006P700000OUsd6": "Alghanim Industries",
  "006P700000MB1SN": "DUBAI WORLD TRADE CENTRE"
 },
 "unresolved": [
  "Turn Well"
 ],
 "ambiguous": {
  "port": [
   "006P700000Zc18e",
   "006P700000FEVJR",
   "006P700000QFJwD",
   "006P700000YlMxa",
   "006P700000VLl6w",
   "006P700000TCnnR",
   "006P700000Q35sD"
  ],
  "Civeo": [
   "006P700000YC92N",
   "006P700000YO8aM"
  ]
 }
}